mediaComp/__init__.py
mediaComp/__init__.pyi
mediaComp/py.typed
mediaComp/assets/error.png
mediaComp/assets/info.png
mediaComp/assets/warning.png
mediaComp/core/__init__.py
mediaComp/core/color.py
mediaComp/core/image.py
mediaComp/core/movie.py
mediaComp/core/sound.py
mediaComp/core/turtle.py
mediaComp/core/utils.py
mediaComp/core/world.py
mediaComp/models/Config.py
mediaComp/models/File_Chooser.py
mediaComp/models/Movie.py
mediaComp/models/Picture.py
mediaComp/models/PixelColor.py
mediaComp/models/Sample.py
mediaComp/models/Samples.py
mediaComp/models/Sound.py
mediaComp/models/SoundExplorer.py
mediaComp/models/SoundSample.py
mediaComp/scripts/colorPicker.py
mediaComp/scripts/filePicker.py
mediaComp/scripts/pictureTool.py
mediaComp/scripts/show.py
mediaComp/scripts/images/Left.png
mediaComp/scripts/images/Right.png
mediacomp-0.4.10.dist-info/METADATA
mediacomp-0.4.10.dist-info/WHEEL
mediacomp-0.4.10.dist-info/licenses/LICENSE
mediacomp-0.4.10.dist-info/RECORD
