Metadata-Version: 2.4
Name: mediaComp
Version: 0.4.10
Summary: A multimedia processing library for Python 3.
Project-URL: Homepage, https://github.com/dllargent/mediaComp
Project-URL: Issues, https://github.com/dllargent/mediaComp/issues
Author-email: A community project <dllargent@bsu.edu>
License-Expression: GPL-3.0-or-later
License-File: LICENSE
Classifier: Operating System :: OS Independent
Classifier: Programming Language :: Python :: 3
Requires-Python: >=3.10
Requires-Dist: matplotlib>=3.10.0
Requires-Dist: numpy>=2.2.1
Requires-Dist: pillow>11.0.0
Requires-Dist: pygame>2.5.0
Requires-Dist: sounddevice>=0.5.2
Provides-Extra: gui
Requires-Dist: wxpython>=4.2.0; extra == 'gui'
